brats_toolkit/__init__.py
brats_toolkit/cli.py
brats_toolkit/config/cpu_dockers.json
brats_toolkit/config/dockers.json
brats_toolkit/config/dockers_demo.json
brats_toolkit/config/fileformats.json
brats_toolkit/config/gpu_dockers.json
brats_toolkit/config/survival_dockers.json
brats_toolkit/fusionator.py
brats_toolkit/preprocessor.py
brats_toolkit/segmentor.py
brats_toolkit/util/__init__.py
brats_toolkit/util/backend_scripts/unix_docker.sh
brats_toolkit/util/backend_scripts/unix_docker_gpu.sh
brats_toolkit/util/backend_scripts/win_docker.cmd
brats_toolkit/util/citation_reminder.py
brats_toolkit/util/docker_functions.py
brats_toolkit/util/filemanager.py
brats_toolkit/util/own_itk.py
brats_toolkit/util/prep_utils.py
brats_toolkit-1.0.18.dist-info/METADATA
brats_toolkit-1.0.18.dist-info/WHEEL
brats_toolkit-1.0.18.dist-info/entry_points.txt
brats_toolkit-1.0.18.dist-info/licenses/LICENSE
brats_toolkit-1.0.18.dist-info/RECORD
