Metadata-Version: 2.4
Name: BraTS-Toolkit
Version: 1.0.18
Summary: BraTS Toolkit is a holistic approach to brain tumor segmentation allowing to build modular pipeliens for preprocessing, segmentation and fusion of segmentations.
License: AGPL-3.0
License-File: LICENSE
Keywords: brain tumor,glioma,BraTS,segmentation,fusion,skullstripping,brain extraction
Author: Florian Kofler
Author-email: florian.kofler@tum.de
Maintainer: Florian Kofler
Maintainer-email: florian.kofler@tum.de
Requires-Python: >=3.10,<4.0
Classifier: License :: OSI Approved :: GNU Affero General Public License v3
Classifier: Operating System :: OS Independent
Classifier: Programming Language :: Python :: 3
Classifier: Programming Language :: Python :: 3.10
Classifier: Programming Language :: Python :: 3.11
Classifier: Programming Language :: Python :: 3.12
Classifier: Programming Language :: Python :: 3.13
Classifier: Programming Language :: Python :: 3.14
Requires-Dist: SimpleITK (>=2.3.1,<3.0.0)
Requires-Dist: numpy (>=1.23.0,<2.0.0)
Requires-Dist: python-engineio (>=3.14.2,<4.0.0)
Requires-Dist: python-socketio (>=4.6.1,<5.0.0)
Requires-Dist: requests (>=2.24.0,<3.0.0)
Requires-Dist: rich (>=13.6.0,<14.0.0)
Project-URL: Documentation, https://brats-toolkit.readthedocs.io/en/latest/
Project-URL: Repository, https://github.com/neuronflow/BraTS-Toolkit
